brunns/__init__.py
brunns/builder/__init__.py
brunns/builder/base.py
brunns/builder/datetime.py
brunns/builder/email.py
brunns/builder/file.py
brunns/builder/internet.py
brunns_builder-1.1.1.dist-info/LICENSE
brunns_builder-1.1.1.dist-info/METADATA
brunns_builder-1.1.1.dist-info/WHEEL
brunns_builder-1.1.1.dist-info/top_level.txt
brunns_builder-1.1.1.dist-info/RECORD
